{
    "name": "betajs-job-scheduler",
    "version": "0.0.4",
    "description": "BetaJS-Job-Scheduler is a framework for handling distributed jobs.",
    "contributors": [
        "Oliver Friedmann",
        "Ziggeo"
    ],
    "devDependencies": {
        "lodash": "",
        "qunitjs": "^2.4.1",
        "grunt": "",
        "grunt-contrib-jshint": "",
        "grunt-contrib-concat": "",
        "grunt-contrib-uglify": "^4.0.0",
        "grunt-contrib-clean": "",
        "grunt-preprocess": "",
        "grunt-closure-tools": "",
        "grunt-jsdoc": "",
        "grunt-shell": "",
        "grunt-githooks": "",
        "grunt-template": "",
        "grunt-benchmark": "",
        "grunt-betajs-docs-compile": "~0.0.19",
        "betajs-scoped": "~0.0.13",
        "betajs-data": "",
        "betajs-compile": "~0.0.28",
        "betajs": "~1.0.141",
        "js-beautify": ""
    },
    "main": "dist/betajs-job-scheduler.js",
    "repository": {
        "type": "git",
        "url": "git://github.com/betajs/betajs-job-scheduler.git"
    },
    "scripts": {
        "test": "grunt check",
        "relink": "npm link betajs && npm link betajs-compile && npm link betajs-scoped && npm link betajs-data",
        "reinstall": "rm -f package-lock.json && rm -rf node_modules && npm i && npm run relink"
    },
    "meta": {
        "sponsors": [
            "Ziggeo"
        ],
        "guid": "70ed7146-bb6d-4da4-97dc-5a8e2d23a23f",
        "badges": {
            "codeclimate": true,
            "travis": true,
            "npm": true,
            "gitter": false
        },
        "weakDependencies": {
            "betajs-scoped": "https://github.com/betajs/betajs-scoped"
        },
        "dependencies": {
            "betajs": "https://github.com/betajs/betajs",
            "betajs-data": "https://github.com/betajs/betajs-data"
        }
    }
}